teloxi/__init__.py
teloxi/version.py
teloxi/core/__init__.py
teloxi/core/auth.py
teloxi/core/client.py
teloxi/core/exception.py
teloxi/core/extend.py
teloxi/core/imports.py
teloxi/device/__init__.py
teloxi/device/api.py
teloxi/device/devices.py
teloxi/extra/__init__.py
teloxi/extra/enums.py
teloxi/extra/features.py
teloxi/extra/link_parser.py
teloxi/extra/objects.py
teloxi/profile/__init__.py
teloxi/profile/generator.py
teloxi/storage/__init__.py
teloxi/storage/database.py
teloxi/utils/__init__.py
teloxi/utils/config.py
teloxi/utils/objects.py
teloxi-1.0.2.dist-info/licenses/LICENSE
teloxi-1.0.2.dist-info/METADATA
teloxi-1.0.2.dist-info/WHEEL
teloxi-1.0.2.dist-info/top_level.txt
teloxi-1.0.2.dist-info/RECORD
