Metadata-Version: 2.4
Name: teloxi
Version: 1.0.2
Summary: A user-friendly library based on Telethon, with additional features and easier usage.
Author-email: Abbas Bachari <abbas-bachari@hotmail.com>
License-Expression: MIT
Project-URL: Homepage, https://github.com/abbas-bachari/teloxi
Project-URL: Documentation, https://github.com/abbas-bachari/teloxi#readme
Project-URL: Source, https://github.com/abbas-bachari/teloxi
Keywords: telethon,telegram,telegram multi session,telegram-python,opentele,openetele,teloxi,dbflux,api,abbas bachari,عباس بچاری
Classifier: Intended Audience :: Developers
Classifier: Programming Language :: Python :: 3.10
Classifier: Programming Language :: Python :: 3.11
Classifier: Programming Language :: Python :: 3.12
Classifier: Operating System :: OS Independent
Requires-Python: >=3.10
License-File: LICENSE
Requires-Dist: loguru>=0.7.3
Requires-Dist: dbflux>=1.0.2
Requires-Dist: telethon>=1.41.2
Requires-Dist: python-socks[asyncio]>=2.7.2
Dynamic: license-file
